issue_downloader/__init__.py
issue_downloader/cli.py
issue_downloader/github_api_query.py
issue_downloader/github_utils.py
issue_downloader/models.py
issue_downloader/settings.py
issue_downloader-1.1.0.dist-info/LICENSE
issue_downloader-1.1.0.dist-info/METADATA
issue_downloader-1.1.0.dist-info/WHEEL
issue_downloader-1.1.0.dist-info/entry_points.txt
issue_downloader-1.1.0.dist-info/top_level.txt
issue_downloader-1.1.0.dist-info/RECORD
