Metadata-Version: 2.1
Name: issue-downloader
Version: 1.1.0
Summary: Downloads issues to Markdown files
Author-email: Viktor Rimark <python@rxbc.se>
Project-URL: repository, https://github.com/vikahl/issue-downloader
Requires-Python: >=3.9
License-File: LICENSE
Requires-Dist: httpx
Requires-Dist: pydantic
Requires-Dist: typer-slim
Provides-Extra: dev
Requires-Dist: issue-downloader[test]; extra == "dev"
Requires-Dist: issue-downloader[types]; extra == "dev"
Requires-Dist: ruff; extra == "dev"
Provides-Extra: test
Requires-Dist: pytest; extra == "test"
Requires-Dist: pytest-cov; extra == "test"
Requires-Dist: respx; extra == "test"
Provides-Extra: types
Requires-Dist: mypy; extra == "types"
